{
  "$id": "https://dash.local/schemas/dashboard.export.output.json",
  "type": "object",
  "required": [
    "request_id",
    "tool_id",
    "status",
    "refs"
  ],
  "properties": {
    "request_id": {
      "type": "string"
    },
    "tool_id": {
      "const": "dashboard.export"
    },
    "status": {
      "type": "string",
      "enum": [
        "ok",
        "failed"
      ]
    },
    "refs": {
      "type": "object",
      "required": [
        "artifact"
      ],
      "properties": {
        "artifact": {
          "$ref": "common.json#/$defs/ArtifactRef"
        }
      },
      "additionalProperties": false
    },
    "warnings": {
      "$ref": "common.json#/$defs/Warnings"
    }
  },
  "additionalProperties": false
}
