{"$id":"https://slides.local/schemas/slides.media_import.input.json","type":"object","required":["request_id","tool_id","context","inputs","params"],"properties":{"request_id":{"type":"string"},"tool_id":{"const":"slides.media_import"},"context":{"$ref":"../common.json#/$defs/ActionContext"},"inputs":{"type":"object","required":["source_type","uri"],"properties":{"source_type":{"type":"string","enum":["local","drive","onedrive","sharepoint","s3"]},"uri":{"type":"string"},"mime":{"type":"string"}},"additionalProperties":false},"params":{"type":"object","additionalProperties":false}},"additionalProperties":false}
